maze_gitb/__init__.py
maze_gitb/game.py
maze_gitb/leaderboard.txt
maze_gitb/main.py
maze_gitb/scene.py
maze_gitb/utils.py
maze_gitb/core/__init__.py
maze_gitb/core/character.py
maze_gitb/core/maze.py
maze_gitb/core/player.py
maze_gitb/core/render.py
maze_gitb/core/sound.py
maze_gitb/core/table.py
maze_gitb/levels/0.json
maze_gitb/levels/1.json
maze_gitb/levels/2.json
maze_gitb/levels/3.json
maze_gitb/levels/4.json
maze_gitb/levels/5.json
maze_gitb/levels/6.json
maze_gitb/levels/7.json
maze_gitb/levels/8.json
maze_gitb/sound/bgm.wav
maze_gitb/sound/enter_box.wav
maze_gitb/sound/first_echo.wav
maze_gitb/sound/hit_wall.wav
maze_gitb/sound/level_up.wav
maze_gitb/sound/second_echo.wav
maze_gitb/sound/start.wav
maze_gitb/sound/wind.wav
maze_gitb-1.0.2.dist-info/LICENSE.txt
maze_gitb-1.0.2.dist-info/METADATA
maze_gitb-1.0.2.dist-info/WHEEL
maze_gitb-1.0.2.dist-info/entry_points.txt
maze_gitb-1.0.2.dist-info/top_level.txt
maze_gitb-1.0.2.dist-info/RECORD
