Metadata-Version: 2.1
Name: maze-gitb
Version: 1.0.2
Summary: A maze game that required users to think inside the box to win
Home-page: https://github.com/Anand1310/summer-code-jam-2021
Author: Benevolent Bonobos
Author-email: jasonho1308@gmail.com
License: MIT
Download-URL: https://github.com/Anand1310/summer-code-jam-2021/archive/v1.0.2.tar.gz
Project-URL: Bug Tracker, https://github.com/Anand1310/summer-code-jam-2021/issues
Keywords: game,maze,box,think inside the box,sound,3d-sound
Platform: UNKNOWN
Classifier: Development Status :: 5 - Production/Stable
Classifier: Intended Audience :: End Users/Desktop
Classifier: License :: OSI Approved :: MIT License
Classifier: Natural Language :: English
Classifier: Operating System :: Microsoft :: Windows
Classifier: Operating System :: Unix
Classifier: Programming Language :: Python :: 3
Classifier: Topic :: Games/Entertainment :: Puzzle Games
Requires-Python: >=3.8.6
License-File: LICENSE.txt
Requires-Dist: blessed
Requires-Dist: numpy
Requires-Dist: PyOpenAL
